data_ecosystem_flask/.env
data_ecosystem_flask/Makefile.ps1
data_ecosystem_flask/__init__.py
data_ecosystem_flask/app.py
data_ecosystem_flask/app_startup.py
data_ecosystem_flask/config/config.dev.json
data_ecosystem_flask/config/config.prod.json
data_ecosystem_flask/config/manifest.json
data_ecosystem_flask/install.py
data_ecosystem_flask/requirements.txt
data_ecosystem_flask/templates/download.html
data_ecosystem_flask/templates/error.html
data_ecosystem_flask/templates/log_file.html
data_ecosystem_flask/templates/upload.html
dev_schema/excel-manifest-schema.xlsx
dev_schema/excel_manifest_schema_for_schemas_sql.xlsx
dev_schema/excel_manifest_schema_for_schemas_sql_merged.xlsx
dev_schema/excel_manifest_schema_for_tables_sql.xlsx
dev_schema/excel_manifest_schema_valuesets.xlsx
dev_schema/json-manifest-schema.json
dev_schema/manifest.schema.json
license.md
ocio/ocio_pade_dev/config/config.dev.json
ocio/ocio_pade_dev/config/config.prod.json
ocio/ocio_pade_dev/config/manifest.json
pyproject.toml
readme.md
setup.cfg
setup.py
data_ecosystem_flask-202307.0.42.dist-info/METADATA
data_ecosystem_flask-202307.0.42.dist-info/WHEEL
data_ecosystem_flask-202307.0.42.dist-info/entry_points.txt
data_ecosystem_flask-202307.0.42.dist-info/RECORD
