Metadata-Version: 2.1
Name: data-ecosystem-flask
Version: 202307.0.42
Summary: Program Agnostic Data Ecosystem (PADE) - Flask Web Service
Home-page: https://test.pypi.org/project/data-ecosystem-services
License: Apache
Author: John Bowyer
Author-email: zfi4@cdc.gov
Requires-Python: >=3.9,<4.0
Classifier: Development Status :: 4 - Beta
Classifier: Environment :: Console
Classifier: Intended Audience :: Developers
Classifier: License :: Other/Proprietary License
Classifier: Operating System :: OS Independent
Classifier: Programming Language :: Python
Classifier: Programming Language :: Python :: 3
Classifier: Programming Language :: Python :: 3.9
Classifier: Programming Language :: Python :: 3.10
Classifier: Programming Language :: Python :: 3.11
Classifier: Programming Language :: Python :: 3.9
Requires-Dist: alation (>=0.1.14,<0.2.0)
Requires-Dist: azure-monitor-opentelemetry-exporter (>=1.0.0b14,<2.0.0)
Requires-Dist: data-ecosystem-services (>=202307.0.41,<202308.0.0)
Requires-Dist: flake8 (>=4.0.1,<5.0.0)
Requires-Dist: flask (>=2.0.0,<3.0.0)
Requires-Dist: flask-restful (>=0.3.10,<0.4.0)
Requires-Dist: flask-restx (>=1.1.0,<2.0.0)
Requires-Dist: numpy (>=1.23.0,<2.0.0)
Requires-Dist: oauthlib (>=3.2.2,<4.0.0)
Requires-Dist: openpyxl (>=3.1.2,<4.0.0)
Requires-Dist: opentelemetry-instrumentation-flask (>=0.39b0,<0.40)
Requires-Dist: opentelemetry-sdk (>=1.17.0,<2.0.0)
Requires-Dist: pycodestyle (>=2.8.0,<2.9.0)
Requires-Dist: python-dotenv (>=1.0.0,<2.0.0)
Requires-Dist: requests (>=2.31.0,<3.0.0)
Requires-Dist: rsconnect (>=0.1.3,<0.2.0)
Requires-Dist: rsconnect-python (>=1.17.1,<2.0.0)
Requires-Dist: setuptools (==65.6.3)
Requires-Dist: six (>=1.16.0,<2.0.0)
Requires-Dist: werkzeug (>=2.3.3,<3.0.0)
Requires-Dist: wrapt (>=1.14.0,<2.0.0)
Requires-Dist: xlsxwriter (>=3.1.0,<4.0.0)
Project-URL: Repository, https://github.com/cdcent/data-ecosystem-services
